zqy/__init__.py
zqy/coord.py
zqy/zqy.py
zqy/zqypath.py
zqy/zqysql.py
zqy-1.0.4.dist-info/DESCRIPTION.rst
zqy-1.0.4.dist-info/METADATA
zqy-1.0.4.dist-info/RECORD
zqy-1.0.4.dist-info/WHEEL
zqy-1.0.4.dist-info/metadata.json
zqy-1.0.4.dist-info/top_level.txt
zqy-1.0.4.dist-info/zip-safe
