Metadata-Version: 2.0
Name: zqy
Version: 1.0.4
Summary: belongs to zqy.
Home-page: http://blog.useasp.net/
Author: zqy
Author-email: 252238741@qq.com
License: MIT
Keywords: bigdata
Platform: UNKNOWN
Classifier: License :: OSI Approved :: MIT License
Classifier: Programming Language :: Python
Classifier: Intended Audience :: Developers
Classifier: Operating System :: OS Independent
